pvqd/__init__.py
pvqd/timing.csv
pvqd-0.1.0.dev5.dist-info/LICENSE
pvqd-0.1.0.dev5.dist-info/METADATA
pvqd-0.1.0.dev5.dist-info/WHEEL
pvqd-0.1.0.dev5.dist-info/top_level.txt
pvqd-0.1.0.dev5.dist-info/RECORD
