Metadata-Version: 2.1
Name: pvqd
Version: 0.1.0.dev5
Summary: Voice Foundation Pathological Voice Quality Database Reader module
License: GPL-2.0 License
Project-URL: Repository, https://github.com/tikuma-lsuhsc/python-pvqd/issues
Project-URL: Issues, https://github.com/tikuma-lsuhsc/python-pvqd/issues
Project-URL: Pull_Requests, https://github.com/tikuma-lsuhsc/python-pvqd/pulls
Keywords: multimedia
Classifier: Development Status :: 3 - Alpha
Classifier: License :: OSI Approved :: GNU General Public License v2 (GPLv2)
Classifier: Topic :: Multimedia :: Sound/Audio
Classifier: Programming Language :: Python :: 3
Requires-Python: >=3.6
License-File: LICENSE
Requires-Dist: pandas
Requires-Dist: numpy
Requires-Dist: openpyxl
